{
  "version": "7",
  "dialect": "postgresql",
  "entries": [
    {
      "idx": 0,
      "version": "7",
      "when": 1776778715675,
      "tag": "0000_initial_schema",
      "breakpoints": true
    },
    {
      "idx": 1,
      "version": "7",
      "when": 1777000000000,
      "tag": "0001_auth_tables",
      "breakpoints": true
    },
    {
      "idx": 2,
      "version": "7",
      "when": 1777100000000,
      "tag": "0002_loop_orders",
      "breakpoints": true
    },
    {
      "idx": 3,
      "version": "7",
      "when": 1777200000000,
      "tag": "0003_watcher_cursors",
      "breakpoints": true
    },
    {
      "idx": 4,
      "version": "7",
      "when": 1777300000000,
      "tag": "0004_orders_redemption",
      "breakpoints": true
    },
    {
      "idx": 5,
      "version": "7",
      "when": 1777400000000,
      "tag": "0005_user_identities",
      "breakpoints": true
    },
    {
      "idx": 6,
      "version": "7",
      "when": 1777500000000,
      "tag": "0006_users_home_currency",
      "breakpoints": true
    },
    {
      "idx": 7,
      "version": "7",
      "when": 1777600000000,
      "tag": "0007_orders_charge_columns",
      "breakpoints": true
    },
    {
      "idx": 8,
      "version": "7",
      "when": 1777700000000,
      "tag": "0008_orders_loop_asset_payment",
      "breakpoints": true
    },
    {
      "idx": 9,
      "version": "7",
      "when": 1777800000000,
      "tag": "0009_users_stellar_address",
      "breakpoints": true
    },
    {
      "idx": 10,
      "version": "7",
      "when": 1777900000000,
      "tag": "0010_pending_payouts",
      "breakpoints": true
    }
  ]
}
